Metadata-Version: 2.1
Name: maxrskiyws
Version: 1.1
Summary: WebSocket for python.
Home-page: UNKNOWN
Author-email: maxrskiy@mail.ru
License: UNKNOWN
Platform: UNKNOWN
